step_economy/__init__.py
step_economy/step_eco.py
stepcord-1.dist-info/METADATA
stepcord-1.dist-info/WHEEL
stepcord-1.dist-info/top_level.txt
stepcord-1.dist-info/RECORD
